{
  "$schema": "https://schema.tauri.app/config/2",
  "productName": "xenotester",
  "version": "0.2.20",
  "identifier": "com.satoshizerocolored.xenotester",
  "build": {
    "beforeDevCommand": "npm run dev",
    "devUrl": "http://localhost:1420",
    "beforeBuildCommand": "npm run build",
    "frontendDist": "../dist"
  },
  "app": {
    "windows": [
      {
        "label": "main",
        "title": "Xenotester",
        "width": 900,
        "height": 700,
        "dragDropEnabled": false
      }
    ],
    "security": {
      "csp": null
    }
  },
  "bundle": {
    "active": true,
    "targets": ["nsis", "app", "dmg"],
    "createUpdaterArtifacts": "v1Compatible",
    "icon": [
      "icons/32x32.png",
      "icons/128x128.png",
      "icons/128x128@2x.png",
      "icons/icon.icns",
      "icons/icon.ico"
    ],
    "macOS": {
      "signingIdentity": "-",
      "hardenedRuntime": true,
      "entitlements": "entitlements.plist",
      "minimumSystemVersion": "10.15"
    }
  },
  "plugins": {
    "updater": {
      "pubkey": "dW50cnVzdGVkIGNvbW1lbnQ6IG1pbmlzaWduIHB1YmxpYyBrZXk6IDJGQzFCRkY3NDdDMEYzRjcKUldUMzg4Qkg5Ny9CTDMyczdaK3BVN051eWVITXZBUjlMalNUWllMQXdFWXVYc0czSFdhUVdER0EK",
      "endpoints": [
        "https://s3-public-presigner-production-b419.up.railway.app/updates/latest.json"
      ]
    }
  }
}
